Metadata-Version: 2.1
Name: odoo14-addon-queue_job
Version: 14.0.3.15.0
Summary: Job Queue
Home-page: https://github.com/OCA/queue
Author: Camptocamp,ACSONE SA/NV,Odoo Community Association (OCA)
Author-email: support@odoo-community.org
License: LGPL-3
Classifier: Programming Language :: Python
Classifier: Framework :: Odoo
Classifier: Framework :: Odoo :: 14.0
Classifier: License :: OSI Approved :: GNU Lesser General Public License v3 (LGPLv3)
Classifier: Development Status :: 6 - Mature
Requires-Python: >=3.6
Requires-Dist: odoo<14.1dev,>=14.0a
Requires-Dist: requests
